[{
	"id": 97,
	"lastVisitTimeLocal": "07.04.2019, 11:58:06",
	"lastVisitTimeUTC": "2019-04-07T08:58:06.067Z",
	"title": "Купить предметы | Магазин Dota 2",
	"url": "https://market.dota2.net/?r=&q=&p=29",
	"typedCount": 0,
	"visitCount": 2
},{
	"id": 96,
	"lastVisitTimeLocal": "07.04.2019, 11:58:03",
	"lastVisitTimeUTC": "2019-04-07T08:58:03.177Z",
	"title": "Купить предметы | Магазин Dota 2",
	"url": "https://market.dota2.net/?r=&q=&p=28",
	"typedCount": 0,
	"visitCount": 2
},{
	"id": 95,
	"lastVisitTimeLocal": "07.04.2019, 11:58:02",
	"lastVisitTimeUTC": "2019-04-07T08:58:02.741Z",
	"title": "Inscribed The Basher Blades | Магазин Dota 2",
	"url": "https://market.dota2.net/item/2312761833-2312761834-Inscribed%20The%20Basher%20Blades/",
	"typedCount": 0,
	"visitCount": 1
},{
	"id": 94,
	"lastVisitTimeLocal": "07.04.2019, 11:58:01",
	"lastVisitTimeUTC": "2019-04-07T08:58:01.074Z",
	"title": "Inscribed The Basher Blades | Магазин Dota 2",
	"url": "https://market.dota2.net/item/2312761835-2312761836-Inscribed%20The%20Basher%20Blades/",
	"typedCount": 0,
	"visitCount": 1
},{
	"id": 93,
	"lastVisitTimeLocal": "07.04.2019, 11:58:00",
	"lastVisitTimeUTC": "2019-04-07T08:58:00.011Z",
	"title": "Offhand Blade of Broken Scale | Магазин Dota 2",
	"url": "https://market.dota2.net/item/2367967467-2665540848-Offhand%20Blade%20of%20Broken%20Scale/",
	"typedCount": 0,
	"visitCount": 1
},{
	"id": 92,
	"lastVisitTimeLocal": "07.04.2019, 11:57:58",
	"lastVisitTimeUTC": "2019-04-07T08:57:58.350Z",
	"title": "Off-Hand Blade of the Fervent Conscript | Магазин Dota 2",
	"url": "https://market.dota2.net/item/2144413670-2710117582-Off-Hand%20Blade%20of%20the%20Fervent%20Conscript/",
	"typedCount": 0,
	"visitCount": 1
},{
	"id": 91,
	"lastVisitTimeLocal": "07.04.2019, 11:57:57",
	"lastVisitTimeUTC": "2019-04-07T08:57:57.408Z",
	"title": "Reprieve of the Clergy Ascetic - Off-Hand | Магазин Dota 2",
	"url": "https://market.dota2.net/item/217224934-2756362832-Reprieve%20of%20the%20Clergy%20Ascetic%20-%20Off-Hand/",
	"typedCount": 0,
	"visitCount": 1
},{
	"id": 90,
	"lastVisitTimeLocal": "07.04.2019, 11:57:52",
	"lastVisitTimeUTC": "2019-04-07T08:57:52.607Z",
	"title": "Купить предметы | Магазин Dota 2",
	"url": "https://market.dota2.net/?r=&q=&p=27",
	"typedCount": 0,
	"visitCount": 2
},{
	"id": 89,
	"lastVisitTimeLocal": "07.04.2019, 11:57:49",
	"lastVisitTimeUTC": "2019-04-07T08:57:49.571Z",
	"title": "Купить предметы | Магазин Dota 2",
	"url": "https://market.dota2.net/?r=&q=&p=26",
	"typedCount": 0,
	"visitCount": 2
},{
	"id": 88,
	"lastVisitTimeLocal": "07.04.2019, 11:57:46",
	"lastVisitTimeUTC": "2019-04-07T08:57:46.659Z",
	"title": "Купить предметы | Магазин Dota 2",
	"url": "https://market.dota2.net/?r=&q=&p=25",
	"typedCount": 0,
	"visitCount": 2
},{
	"id": 87,
	"lastVisitTimeLocal": "07.04.2019, 11:57:45",
	"lastVisitTimeUTC": "2019-04-07T08:57:45.808Z",
	"title": "Купить предметы | Магазин Dota 2",
	"url": "https://market.dota2.net/?r=&q=&p=24",
	"typedCount": 0,
	"visitCount": 2
},{
	"id": 86,
	"lastVisitTimeLocal": "07.04.2019, 11:57:44",
	"lastVisitTimeUTC": "2019-04-07T08:57:44.489Z",
	"title": "Купить предметы | Магазин Dota 2",
	"url": "https://market.dota2.net/?r=&q=&p=23",
	"typedCount": 0,
	"visitCount": 2
},{
	"id": 85,
	"lastVisitTimeLocal": "07.04.2019, 11:57:43",
	"lastVisitTimeUTC": "2019-04-07T08:57:43.215Z",
	"title": "Купить предметы | Магазин Dota 2",
	"url": "https://market.dota2.net/?r=&q=&p=22",
	"typedCount": 0,
	"visitCount": 2
},{
	"id": 84,
	"lastVisitTimeLocal": "07.04.2019, 11:57:41",
	"lastVisitTimeUTC": "2019-04-07T08:57:41.061Z",
	"title": "Купить предметы | Магазин Dota 2",
	"url": "https://market.dota2.net/?r=&q=&p=21",
	"typedCount": 0,
	"visitCount": 2
},{
	"id": 83,
	"lastVisitTimeLocal": "07.04.2019, 11:57:39",
	"lastVisitTimeUTC": "2019-04-07T08:57:39.876Z",
	"title": "Купить предметы | Магазин Dota 2",
	"url": "https://market.dota2.net/?r=&q=&p=20",
	"typedCount": 0,
	"visitCount": 2
},{
	"id": 82,
	"lastVisitTimeLocal": "07.04.2019, 11:57:38",
	"lastVisitTimeUTC": "2019-04-07T08:57:38.767Z",
	"title": "Купить предметы | Магазин Dota 2",
	"url": "https://market.dota2.net/?r=&q=&p=19",
	"typedCount": 0,
	"visitCount": 2
},{
	"id": 81,
	"lastVisitTimeLocal": "07.04.2019, 11:57:36",
	"lastVisitTimeUTC": "2019-04-07T08:57:36.373Z",
	"title": "Купить предметы | Магазин Dota 2",
	"url": "https://market.dota2.net/?r=&q=&p=18",
	"typedCount": 0,
	"visitCount": 2
},{
	"id": 80,
	"lastVisitTimeLocal": "07.04.2019, 11:57:33",
	"lastVisitTimeUTC": "2019-04-07T08:57:33.552Z",
	"title": "Купить предметы | Магазин Dota 2",
	"url": "https://market.dota2.net/?r=&q=&p=17",
	"typedCount": 0,
	"visitCount": 2
},{
	"id": 79,
	"lastVisitTimeLocal": "07.04.2019, 11:57:29",
	"lastVisitTimeUTC": "2019-04-07T08:57:29.252Z",
	"title": "Купить предметы | Магазин Dota 2",
	"url": "https://market.dota2.net/?r=&q=&p=16",
	"typedCount": 0,
	"visitCount": 2
},{
	"id": 78,
	"lastVisitTimeLocal": "07.04.2019, 11:57:20",
	"lastVisitTimeUTC": "2019-04-07T08:57:20.848Z",
	"title": "Купить предметы | Магазин Dota 2",
	"url": "https://market.dota2.net/?r=&q=&p=15",
	"typedCount": 0,
	"visitCount": 2
},{
	"id": 77,
	"lastVisitTimeLocal": "07.04.2019, 11:57:17",
	"lastVisitTimeUTC": "2019-04-07T08:57:17.664Z",
	"title": "Купить предметы | Магазин Dota 2",
	"url": "https://market.dota2.net/?r=&q=&p=14",
	"typedCount": 0,
	"visitCount": 2
},{
	"id": 76,
	"lastVisitTimeLocal": "07.04.2019, 11:57:15",
	"lastVisitTimeUTC": "2019-04-07T08:57:15.732Z",
	"title": "Купить предметы | Магазин Dota 2",
	"url": "https://market.dota2.net/?r=&q=&p=13",
	"typedCount": 0,
	"visitCount": 2
},{
	"id": 75,
	"lastVisitTimeLocal": "07.04.2019, 11:56:23",
	"lastVisitTimeUTC": "2019-04-07T08:56:23.742Z",
	"title": "Купить предметы | Магазин Dota 2",
	"url": "https://market.dota2.net/?r=&q=&p=12",
	"typedCount": 0,
	"visitCount": 2
},{
	"id": 74,
	"lastVisitTimeLocal": "07.04.2019, 11:56:22",
	"lastVisitTimeUTC": "2019-04-07T08:56:22.178Z",
	"title": "Etched Crescent of Yoskreth — Off-Hand | Магазин Dota 2",
	"url": "https://market.dota2.net/item/1806946150-3197882625-Etched%20Crescent%20of%20Yoskreth%20%E2%80%94%20Off-Hand/",
	"typedCount": 0,
	"visitCount": 1
},{
	"id": 73,
	"lastVisitTimeLocal": "07.04.2019, 11:56:18",
	"lastVisitTimeUTC": "2019-04-07T08:56:18.686Z",
	"title": "Купить предметы | Магазин Dota 2",
	"url": "https://market.dota2.net/?r=&q=&p=11",
	"typedCount": 0,
	"visitCount": 2
},{
	"id": 72,
	"lastVisitTimeLocal": "07.04.2019, 11:56:16",
	"lastVisitTimeUTC": "2019-04-07T08:56:16.386Z",
	"title": "Купить предметы | Магазин Dota 2",
	"url": "https://market.dota2.net/?r=&q=&p=10",
	"typedCount": 0,
	"visitCount": 2
},{
	"id": 71,
	"lastVisitTimeLocal": "07.04.2019, 11:56:14",
	"lastVisitTimeUTC": "2019-04-07T08:56:14.727Z",
	"title": "Inscribed Acolyte of Vengeance Weapon | Магазин Dota 2",
	"url": "https://market.dota2.net/item/503280484-1625728520-Inscribed%20Acolyte%20of%20Vengeance%20Weapon/",
	"typedCount": 0,
	"visitCount": 1
},{
	"id": 70,
	"lastVisitTimeLocal": "07.04.2019, 11:56:12",
	"lastVisitTimeUTC": "2019-04-07T08:56:12.078Z",
	"title": "Inscribed The Basher Blades | Магазин Dota 2",
	"url": "https://market.dota2.net/item/2318141284-2318141285-Inscribed%20The%20Basher%20Blades/",
	"typedCount": 0,
	"visitCount": 1
},{
	"id": 69,
	"lastVisitTimeLocal": "07.04.2019, 11:56:11",
	"lastVisitTimeUTC": "2019-04-07T08:56:11.489Z",
	"title": "Offhand Basher of Mage Skulls | Магазин Dota 2",
	"url": "https://market.dota2.net/item/997187938-3194133018-Offhand%20Basher%20of%20Mage%20Skulls/",
	"typedCount": 0,
	"visitCount": 1
},{
	"id": 68,
	"lastVisitTimeLocal": "07.04.2019, 11:56:10",
	"lastVisitTimeUTC": "2019-04-07T08:56:10.958Z",
	"title": "Arc of Manta | Магазин Dota 2",
	"url": "https://market.dota2.net/item/887396194-0-Arc%20of%20Manta/",
	"typedCount": 0,
	"visitCount": 1
},{
	"id": 67,
	"lastVisitTimeLocal": "07.04.2019, 11:56:03",
	"lastVisitTimeUTC": "2019-04-07T08:56:03.697Z",
	"title": "Купить предметы | Магазин Dota 2",
	"url": "https://market.dota2.net/?r=&q=&p=9",
	"typedCount": 0,
	"visitCount": 2
},{
	"id": 66,
	"lastVisitTimeLocal": "07.04.2019, 11:56:02",
	"lastVisitTimeUTC": "2019-04-07T08:56:02.709Z",
	"title": "Blade of the Fervent Conscript | Магазин Dota 2",
	"url": "https://market.dota2.net/item/2169672515-2946872850-Blade%20of%20the%20Fervent%20Conscript/",
	"typedCount": 0,
	"visitCount": 1
},{
	"id": 65,
	"lastVisitTimeLocal": "07.04.2019, 11:56:02",
	"lastVisitTimeUTC": "2019-04-07T08:56:02.319Z",
	"title": "Autographed Off-Hand Blade of the Fervent Conscript | Магазин Dota 2",
	"url": "https://market.dota2.net/item/2166242111-3186636930-Autographed%20Off-Hand%20Blade%20of%20the%20Fervent%20Conscript/",
	"typedCount": 0,
	"visitCount": 1
},{
	"id": 64,
	"lastVisitTimeLocal": "07.04.2019, 11:56:00",
	"lastVisitTimeUTC": "2019-04-07T08:56:00.733Z",
	"title": "Genuine Blade of Tustakuri | Магазин Dota 2",
	"url": "https://market.dota2.net/item/768273231-1193964688-Genuine%20Blade%20of%20Tustakuri/",
	"typedCount": 0,
	"visitCount": 1
},{
	"id": 63,
	"lastVisitTimeLocal": "07.04.2019, 11:55:59",
	"lastVisitTimeUTC": "2019-04-07T08:55:59.760Z",
	"title": "Genuine Blade of Tustakuri - Off-Hand | Магазин Dota 2",
	"url": "https://market.dota2.net/item/768273229-2078277662-Genuine%20Blade%20of%20Tustakuri%20-%20Off-Hand/",
	"typedCount": 0,
	"visitCount": 1
},{
	"id": 62,
	"lastVisitTimeLocal": "07.04.2019, 11:55:56",
	"lastVisitTimeUTC": "2019-04-07T08:55:56.293Z",
	"title": "Купить предметы | Магазин Dota 2",
	"url": "https://market.dota2.net/?r=&q=&p=8",
	"typedCount": 0,
	"visitCount": 2
},{
	"id": 61,
	"lastVisitTimeLocal": "07.04.2019, 11:55:50",
	"lastVisitTimeUTC": "2019-04-07T08:55:50.245Z",
	"title": "Купить предметы | Магазин Dota 2",
	"url": "https://market.dota2.net/?r=&q=&p=7",
	"typedCount": 0,
	"visitCount": 2
},{
	"id": 60,
	"lastVisitTimeLocal": "07.04.2019, 11:55:34",
	"lastVisitTimeUTC": "2019-04-07T08:55:34.124Z",
	"title": "Inscribed The Basher Blades | Магазин Dota 2",
	"url": "https://market.dota2.net/item/2358428674-2358428676-Inscribed%20The%20Basher%20Blades/",
	"typedCount": 0,
	"visitCount": 1
},{
	"id": 59,
	"lastVisitTimeLocal": "07.04.2019, 11:55:27",
	"lastVisitTimeUTC": "2019-04-07T08:55:27.548Z",
	"title": "Купить предметы | Магазин Dota 2",
	"url": "https://market.dota2.net/?r=&q=&p=6",
	"typedCount": 0,
	"visitCount": 2
},{
	"id": 58,
	"lastVisitTimeLocal": "07.04.2019, 11:55:26",
	"lastVisitTimeUTC": "2019-04-07T08:55:26.045Z",
	"title": "Nomad's Barbed Edge | Магазин Dota 2",
	"url": "https://market.dota2.net/item/172567484-0-Nomad's%20Barbed%20Edge/",
	"typedCount": 0,
	"visitCount": 1
},{
	"id": 57,
	"lastVisitTimeLocal": "07.04.2019, 11:55:22",
	"lastVisitTimeUTC": "2019-04-07T08:55:22.856Z",
	"title": "Hatchet of the Shifting Sorcerer - Offhand | Магазин Dota 2",
	"url": "https://market.dota2.net/item/230131879-230357228-Hatchet%20of%20the%20Shifting%20Sorcerer%20-%20Offhand/",
	"typedCount": 0,
	"visitCount": 1
},{
	"id": 56,
	"lastVisitTimeLocal": "07.04.2019, 11:55:22",
	"lastVisitTimeUTC": "2019-04-07T08:55:22.311Z",
	"title": "Glaive of the Mage Slayer - Off-Hand | Магазин Dota 2",
	"url": "https://market.dota2.net/item/93966752-0-Glaive%20of%20the%20Mage%20Slayer%20-%20Off-Hand/",
	"typedCount": 0,
	"visitCount": 1
},{
	"id": 55,
	"lastVisitTimeLocal": "07.04.2019, 11:55:00",
	"lastVisitTimeUTC": "2019-04-07T08:55:00.072Z",
	"title": "Купить предметы | Магазин Dota 2",
	"url": "https://market.dota2.net/?r=&q=&p=5",
	"typedCount": 0,
	"visitCount": 2
},{
	"id": 54,
	"lastVisitTimeLocal": "07.04.2019, 11:54:59",
	"lastVisitTimeUTC": "2019-04-07T08:54:59.289Z",
	"title": "Inscribed Ancient Crescent | Магазин Dota 2",
	"url": "https://market.dota2.net/item/231965461-230151668-Inscribed%20Ancient%20Crescent/",
	"typedCount": 0,
	"visitCount": 1
},{
	"id": 53,
	"lastVisitTimeLocal": "07.04.2019, 11:54:57",
	"lastVisitTimeUTC": "2019-04-07T08:54:57.854Z",
	"title": "Reprieve of the Clergy Ascetic | Магазин Dota 2",
	"url": "https://market.dota2.net/item/217224936-622668187-Reprieve%20of%20the%20Clergy%20Ascetic/",
	"typedCount": 0,
	"visitCount": 1
},{
	"id": 52,
	"lastVisitTimeLocal": "07.04.2019, 11:54:56",
	"lastVisitTimeUTC": "2019-04-07T08:54:56.613Z",
	"title": "Cursed Nomad's Edge - Off-Hand | Магазин Dota 2",
	"url": "https://market.dota2.net/item/230247653-0-Cursed%20Nomad's%20Edge%20-%20Off-Hand/",
	"typedCount": 0,
	"visitCount": 1
},{
	"id": 51,
	"lastVisitTimeLocal": "07.04.2019, 11:54:55",
	"lastVisitTimeUTC": "2019-04-07T08:54:55.088Z",
	"title": "Nomad's Edge - Off-Hand | Магазин Dota 2",
	"url": "https://market.dota2.net/item/172567486-0-Nomad's%20Edge%20-%20Off-Hand/",
	"typedCount": 0,
	"visitCount": 1
},{
	"id": 50,
	"lastVisitTimeLocal": "07.04.2019, 11:54:51",
	"lastVisitTimeUTC": "2019-04-07T08:54:51.763Z",
	"title": "Inscribed The Basher Blades | Магазин Dota 2",
	"url": "https://market.dota2.net/item/996698450-253033329-Inscribed%20The%20Basher%20Blades/",
	"typedCount": 0,
	"visitCount": 1
},{
	"id": 49,
	"lastVisitTimeLocal": "07.04.2019, 11:54:50",
	"lastVisitTimeUTC": "2019-04-07T08:54:50.750Z",
	"title": "Ancient Crasher | Магазин Dota 2",
	"url": "https://market.dota2.net/item/138051107-0-Ancient%20Crasher/",
	"typedCount": 0,
	"visitCount": 1
},{
	"id": 48,
	"lastVisitTimeLocal": "07.04.2019, 11:54:49",
	"lastVisitTimeUTC": "2019-04-07T08:54:49.086Z",
	"title": "Inscribed Ancient Crescent | Магазин Dota 2",
	"url": "https://market.dota2.net/item/231965461-253057424-Inscribed%20Ancient%20Crescent/",
	"typedCount": 0,
	"visitCount": 1
},{
	"id": 47,
	"lastVisitTimeLocal": "07.04.2019, 11:54:46",
	"lastVisitTimeUTC": "2019-04-07T08:54:46.113Z",
	"title": "Купить предметы | Магазин Dota 2",
	"url": "https://market.dota2.net/?r=&q=&p=4",
	"typedCount": 0,
	"visitCount": 2
},{
	"id": 46,
	"lastVisitTimeLocal": "07.04.2019, 11:54:43",
	"lastVisitTimeUTC": "2019-04-07T08:54:43.886Z",
	"title": "Glaive of the Mage Slayer | Магазин Dota 2",
	"url": "https://market.dota2.net/item/93966749-675504371-Glaive%20of%20the%20Mage%20Slayer/",
	"typedCount": 0,
	"visitCount": 1
},{
	"id": 45,
	"lastVisitTimeLocal": "07.04.2019, 11:54:42",
	"lastVisitTimeUTC": "2019-04-07T08:54:42.706Z",
	"title": "Blade of the Witch Hunter | Магазин Dota 2",
	"url": "https://market.dota2.net/item/521516671-625682205-Blade%20of%20the%20Witch%20Hunter/",
	"typedCount": 0,
	"visitCount": 1
},{
	"id": 44,
	"lastVisitTimeLocal": "07.04.2019, 11:54:39",
	"lastVisitTimeUTC": "2019-04-07T08:54:39.399Z",
	"title": "Inscribed The Basher Blades | Магазин Dota 2",
	"url": "https://market.dota2.net/item/996698450-253032902-Inscribed%20The%20Basher%20Blades/",
	"typedCount": 0,
	"visitCount": 1
},{
	"id": 43,
	"lastVisitTimeLocal": "07.04.2019, 11:54:37",
	"lastVisitTimeUTC": "2019-04-07T08:54:37.436Z",
	"title": "Genuine Blade of Tustakuri | Магазин Dota 2",
	"url": "https://market.dota2.net/item/768273231-0-Genuine%20Blade%20of%20Tustakuri/",
	"typedCount": 0,
	"visitCount": 1
},{
	"id": 42,
	"lastVisitTimeLocal": "07.04.2019, 11:54:36",
	"lastVisitTimeUTC": "2019-04-07T08:54:36.866Z",
	"title": "Acolyte of Vengeance Offhand | Магазин Dota 2",
	"url": "https://market.dota2.net/item/502993858-523337946-Acolyte%20of%20Vengeance%20Offhand/",
	"typedCount": 0,
	"visitCount": 1
},{
	"id": 41,
	"lastVisitTimeLocal": "07.04.2019, 11:54:31",
	"lastVisitTimeUTC": "2019-04-07T08:54:31.966Z",
	"title": "Купить предметы | Магазин Dota 2",
	"url": "https://market.dota2.net/?r=&q=&p=3",
	"typedCount": 0,
	"visitCount": 2
},{
	"id": 40,
	"lastVisitTimeLocal": "07.04.2019, 11:54:18",
	"lastVisitTimeUTC": "2019-04-07T08:54:18.111Z",
	"title": "Набор «The Gifts of Yoskreth» | Магазин Dota 2",
	"url": "https://market.dota2.net/item/122679163-0-%D0%9D%D0%B0%D0%B1%D0%BE%D1%80%20%C2%ABThe%20Gifts%20of%20Yoskreth%C2%BB/",
	"typedCount": 0,
	"visitCount": 1
},{
	"id": 39,
	"lastVisitTimeLocal": "07.04.2019, 11:54:09",
	"lastVisitTimeUTC": "2019-04-07T08:54:09.650Z",
	"title": "Golden Basher of Mage Skulls | Магазин Dota 2",
	"url": "https://market.dota2.net/item/996713688-1205068206-Golden%20Basher%20of%20Mage%20Skulls/",
	"typedCount": 0,
	"visitCount": 1
},{
	"id": 38,
	"lastVisitTimeLocal": "07.04.2019, 11:54:05",
	"lastVisitTimeUTC": "2019-04-07T08:54:05.614Z",
	"title": "Glaive of the Mage Slayer | Магазин Dota 2",
	"url": "https://market.dota2.net/item/93966749-0-Glaive%20of%20the%20Mage%20Slayer/",
	"typedCount": 0,
	"visitCount": 1
},{
	"id": 37,
	"lastVisitTimeLocal": "07.04.2019, 11:54:03",
	"lastVisitTimeUTC": "2019-04-07T08:54:03.808Z",
	"title": "Offhand Basher of Mage Skulls | Магазин Dota 2",
	"url": "https://market.dota2.net/item/996701649-1251204815-Offhand%20Basher%20of%20Mage%20Skulls/",
	"typedCount": 0,
	"visitCount": 1
},{
	"id": 36,
	"lastVisitTimeLocal": "07.04.2019, 11:54:03",
	"lastVisitTimeUTC": "2019-04-07T08:54:03.126Z",
	"title": "Glaive of the Mage Slayer - Off-Hand | Магазин Dota 2",
	"url": "https://market.dota2.net/item/93966752-626080326-Glaive%20of%20the%20Mage%20Slayer%20-%20Off-Hand/",
	"typedCount": 0,
	"visitCount": 1
},{
	"id": 35,
	"lastVisitTimeLocal": "07.04.2019, 11:54:02",
	"lastVisitTimeUTC": "2019-04-07T08:54:02.645Z",
	"title": "Shard of Vengeance | Магазин Dota 2",
	"url": "https://market.dota2.net/item/247762048-633772512-Shard%20of%20Vengeance/",
	"typedCount": 0,
	"visitCount": 1
},{
	"id": 34,
	"lastVisitTimeLocal": "07.04.2019, 11:53:59",
	"lastVisitTimeUTC": "2019-04-07T08:53:59.962Z",
	"title": "Genuine Blade of Tustakuri - Off-Hand | Магазин Dota 2",
	"url": "https://market.dota2.net/item/768273229-0-Genuine%20Blade%20of%20Tustakuri%20-%20Off-Hand/",
	"typedCount": 0,
	"visitCount": 1
},{
	"id": 33,
	"lastVisitTimeLocal": "07.04.2019, 11:53:57",
	"lastVisitTimeUTC": "2019-04-07T08:53:57.631Z",
	"title": "Hatchet of the Shifting Sorcerer - Offhand | Магазин Dota 2",
	"url": "https://market.dota2.net/item/230131879-625944709-Hatchet%20of%20the%20Shifting%20Sorcerer%20-%20Offhand/",
	"typedCount": 0,
	"visitCount": 1
},{
	"id": 32,
	"lastVisitTimeLocal": "07.04.2019, 11:53:56",
	"lastVisitTimeUTC": "2019-04-07T08:53:56.768Z",
	"title": "Hatchet of the Shifting Sorcerer | Магазин Dota 2",
	"url": "https://market.dota2.net/item/230131882-625944709-Hatchet%20of%20the%20Shifting%20Sorcerer/",
	"typedCount": 0,
	"visitCount": 1
},{
	"id": 31,
	"lastVisitTimeLocal": "07.04.2019, 11:53:56",
	"lastVisitTimeUTC": "2019-04-07T08:53:56.055Z",
	"title": "Offhand Blade of Broken Scale | Магазин Dota 2",
	"url": "https://market.dota2.net/item/1479302876-0-Offhand%20Blade%20of%20Broken%20Scale/",
	"typedCount": 0,
	"visitCount": 1
},{
	"id": 30,
	"lastVisitTimeLocal": "07.04.2019, 11:53:55",
	"lastVisitTimeUTC": "2019-04-07T08:53:55.485Z",
	"title": "Acolyte of Vengeance Weapon | Магазин Dota 2",
	"url": "https://market.dota2.net/item/502993860-523337946-Acolyte%20of%20Vengeance%20Weapon/",
	"typedCount": 0,
	"visitCount": 1
},{
	"id": 29,
	"lastVisitTimeLocal": "07.04.2019, 11:53:54",
	"lastVisitTimeUTC": "2019-04-07T08:53:54.504Z",
	"title": "Blade of Broken Scale | Магазин Dota 2",
	"url": "https://market.dota2.net/item/1479302881-0-Blade%20of%20Broken%20Scale/",
	"typedCount": 0,
	"visitCount": 1
},{
	"id": 28,
	"lastVisitTimeLocal": "07.04.2019, 11:53:51",
	"lastVisitTimeUTC": "2019-04-07T08:53:51.045Z",
	"title": "Купить предметы | Магазин Dota 2",
	"url": "https://market.dota2.net/?r=&q=&p=2",
	"typedCount": 0,
	"visitCount": 2
},{
	"id": 27,
	"lastVisitTimeLocal": "07.04.2019, 11:53:48",
	"lastVisitTimeUTC": "2019-04-07T08:53:48.517Z",
	"title": "Offhand Blade of the Survivor | Магазин Dota 2",
	"url": "https://market.dota2.net/item/1987660921-1625510296-Offhand%20Blade%20of%20the%20Survivor/",
	"typedCount": 0,
	"visitCount": 2
},{
	"id": 26,
	"lastVisitTimeLocal": "07.04.2019, 11:53:44",
	"lastVisitTimeUTC": "2019-04-07T08:53:44.126Z",
	"title": "Blade of the Survivor | Магазин Dota 2",
	"url": "https://market.dota2.net/item/1987660923-1625510296-Blade%20of%20the%20Survivor/",
	"typedCount": 0,
	"visitCount": 1
},{
	"id": 25,
	"lastVisitTimeLocal": "07.04.2019, 11:53:42",
	"lastVisitTimeUTC": "2019-04-07T08:53:42.689Z",
	"title": "Golden Basher of Mage Skulls | Магазин Dota 2",
	"url": "https://market.dota2.net/item/996713688-0-Golden%20Basher%20of%20Mage%20Skulls/",
	"typedCount": 0,
	"visitCount": 1
},{
	"id": 24,
	"lastVisitTimeLocal": "07.04.2019, 11:53:41",
	"lastVisitTimeUTC": "2019-04-07T08:53:41.344Z",
	"title": "Golden Offhand Basher of Mage Skulls | Магазин Dota 2",
	"url": "https://market.dota2.net/item/996714933-0-Golden%20Offhand%20Basher%20of%20Mage%20Skulls/",
	"typedCount": 0,
	"visitCount": 1
},{
	"id": 23,
	"lastVisitTimeLocal": "07.04.2019, 11:53:31",
	"lastVisitTimeUTC": "2019-04-07T08:53:31.954Z",
	"title": "Off-Hand of the Dragon's Disciple | Магазин Dota 2",
	"url": "https://market.dota2.net/item/3099884863-1625510296-Off-Hand%20of%20the%20Dragon's%20Disciple/",
	"typedCount": 0,
	"visitCount": 1
},{
	"id": 22,
	"lastVisitTimeLocal": "07.04.2019, 11:53:29",
	"lastVisitTimeUTC": "2019-04-07T08:53:29.189Z",
	"title": "Arc of Manta - Off-Hand | Магазин Dota 2",
	"url": "https://market.dota2.net/item/200340051-0-Arc%20of%20Manta%20-%20Off-Hand/",
	"typedCount": 0,
	"visitCount": 1
},{
	"id": 21,
	"lastVisitTimeLocal": "07.04.2019, 11:53:23",
	"lastVisitTimeUTC": "2019-04-07T08:53:23.609Z",
	"title": "Off-Hand Blade of the Fervent Conscript | Магазин Dota 2",
	"url": "https://market.dota2.net/item/2144413670-1625510600-Off-Hand%20Blade%20of%20the%20Fervent%20Conscript/",
	"typedCount": 0,
	"visitCount": 1
},{
	"id": 20,
	"lastVisitTimeLocal": "07.04.2019, 11:53:19",
	"lastVisitTimeUTC": "2019-04-07T08:53:19.293Z",
	"title": "Offhand Basher of Mage Skulls | Магазин Dota 2",
	"url": "https://market.dota2.net/item/996701649-0-Offhand%20Basher%20of%20Mage%20Skulls/",
	"typedCount": 0,
	"visitCount": 1
},{
	"id": 19,
	"lastVisitTimeLocal": "07.04.2019, 11:53:18",
	"lastVisitTimeUTC": "2019-04-07T08:53:18.844Z",
	"title": "Basher of Mage Skulls | Магазин Dota 2",
	"url": "https://market.dota2.net/item/996695916-0-Basher%20of%20Mage%20Skulls/",
	"typedCount": 0,
	"visitCount": 1
}]