[{
	"id": 76,
	"lastVisitTimeLocal": "07.04.2019, 13:21:53",
	"lastVisitTimeUTC": "2019-04-07T10:21:53.917Z",
	"title": "Купить предметы | Магазин Dota 2",
	"url": "https://market.dota2.net/?r=&q=&p=15",
	"typedCount": 0,
	"visitCount": 2
},{
	"id": 75,
	"lastVisitTimeLocal": "07.04.2019, 13:21:47",
	"lastVisitTimeUTC": "2019-04-07T10:21:47.752Z",
	"title": "Купить предметы | Магазин Dota 2",
	"url": "https://market.dota2.net/?r=&q=&p=14",
	"typedCount": 0,
	"visitCount": 2
},{
	"id": 74,
	"lastVisitTimeLocal": "07.04.2019, 13:21:41",
	"lastVisitTimeUTC": "2019-04-07T10:21:41.408Z",
	"title": "Купить предметы | Магазин Dota 2",
	"url": "https://market.dota2.net/?r=&q=&p=13",
	"typedCount": 0,
	"visitCount": 2
},{
	"id": 73,
	"lastVisitTimeLocal": "07.04.2019, 13:21:40",
	"lastVisitTimeUTC": "2019-04-07T10:21:40.650Z",
	"title": "Inscribed Bow of the Eldwurm's Touch | Магазин Dota 2",
	"url": "https://market.dota2.net/item/631058361-253039038-Inscribed%20Bow%20of%20the%20Eldwurm's%20Touch/",
	"typedCount": 0,
	"visitCount": 1
},{
	"id": 72,
	"lastVisitTimeLocal": "07.04.2019, 13:21:40",
	"lastVisitTimeUTC": "2019-04-07T10:21:40.137Z",
	"title": "Inscribed Bow of the Eldwurm's Touch | Магазин Dota 2",
	"url": "https://market.dota2.net/item/631058361-2170700075-Inscribed%20Bow%20of%20the%20Eldwurm's%20Touch/",
	"typedCount": 0,
	"visitCount": 1
},{
	"id": 71,
	"lastVisitTimeLocal": "07.04.2019, 13:21:36",
	"lastVisitTimeUTC": "2019-04-07T10:21:36.599Z",
	"title": "Bow of the Frostfangs | Магазин Dota 2",
	"url": "https://market.dota2.net/item/782548140-2041129387-Bow%20of%20the%20Frostfangs/",
	"typedCount": 0,
	"visitCount": 1
},{
	"id": 70,
	"lastVisitTimeLocal": "07.04.2019, 13:21:34",
	"lastVisitTimeUTC": "2019-04-07T10:21:34.568Z",
	"title": "Inscribed Pincher Bow | Магазин Dota 2",
	"url": "https://market.dota2.net/item/177828011-253033266-Inscribed%20Pincher%20Bow/",
	"typedCount": 0,
	"visitCount": 1
},{
	"id": 69,
	"lastVisitTimeLocal": "07.04.2019, 13:21:34",
	"lastVisitTimeUTC": "2019-04-07T10:21:34.525Z",
	"title": "Inscribed Sylvan Guard's Bow | Магазин Dota 2",
	"url": "https://market.dota2.net/item/177854124-253041574-Inscribed%20Sylvan%20Guard's%20Bow/",
	"typedCount": 0,
	"visitCount": 1
},{
	"id": 68,
	"lastVisitTimeLocal": "07.04.2019, 13:21:32",
	"lastVisitTimeUTC": "2019-04-07T10:21:32.501Z",
	"title": "Jewel of the Forest Bow | Магазин Dota 2",
	"url": "https://market.dota2.net/item/190098341-675292913-Jewel%20of%20the%20Forest%20Bow/",
	"typedCount": 0,
	"visitCount": 1
},{
	"id": 67,
	"lastVisitTimeLocal": "07.04.2019, 13:21:30",
	"lastVisitTimeUTC": "2019-04-07T10:21:30.101Z",
	"title": "Купить предметы | Магазин Dota 2",
	"url": "https://market.dota2.net/?r=&q=&p=12",
	"typedCount": 0,
	"visitCount": 2
},{
	"id": 66,
	"lastVisitTimeLocal": "07.04.2019, 13:21:28",
	"lastVisitTimeUTC": "2019-04-07T10:21:28.920Z",
	"title": "Genuine Bow of the Howling Wind | Магазин Dota 2",
	"url": "https://market.dota2.net/item/667442844-2097268733-Genuine%20Bow%20of%20the%20Howling%20Wind/",
	"typedCount": 0,
	"visitCount": 1
},{
	"id": 65,
	"lastVisitTimeLocal": "07.04.2019, 13:21:23",
	"lastVisitTimeUTC": "2019-04-07T10:21:23.625Z",
	"title": "Купить предметы | Магазин Dota 2",
	"url": "https://market.dota2.net/?r=&q=&p=11",
	"typedCount": 0,
	"visitCount": 2
},{
	"id": 64,
	"lastVisitTimeLocal": "07.04.2019, 13:21:20",
	"lastVisitTimeUTC": "2019-04-07T10:21:20.584Z",
	"title": "Inscribed Bow of the Wyvern Skin | Магазин Dota 2",
	"url": "https://market.dota2.net/item/985079931-1731778856-Inscribed%20Bow%20of%20the%20Wyvern%20Skin/",
	"typedCount": 0,
	"visitCount": 1
},{
	"id": 63,
	"lastVisitTimeLocal": "07.04.2019, 13:21:18",
	"lastVisitTimeUTC": "2019-04-07T10:21:18.136Z",
	"title": "Inscribed Bow of the Crystal Caves | Магазин Dota 2",
	"url": "https://market.dota2.net/item/231230089-253074440-Inscribed%20Bow%20of%20the%20Crystal%20Caves/",
	"typedCount": 0,
	"visitCount": 1
},{
	"id": 62,
	"lastVisitTimeLocal": "07.04.2019, 13:21:15",
	"lastVisitTimeUTC": "2019-04-07T10:21:15.663Z",
	"title": "Купить предметы | Магазин Dota 2",
	"url": "https://market.dota2.net/?r=&q=&p=10",
	"typedCount": 0,
	"visitCount": 2
},{
	"id": 61,
	"lastVisitTimeLocal": "07.04.2019, 13:21:15",
	"lastVisitTimeUTC": "2019-04-07T10:21:15.266Z",
	"title": "Cold Case Bow | Магазин Dota 2",
	"url": "https://market.dota2.net/item/57939576-230149949-Cold%20Case%20Bow/",
	"typedCount": 0,
	"visitCount": 1
},{
	"id": 60,
	"lastVisitTimeLocal": "07.04.2019, 13:21:13",
	"lastVisitTimeUTC": "2019-04-07T10:21:13.971Z",
	"title": "Inscribed Sylvan Guard's Bow | Магазин Dota 2",
	"url": "https://market.dota2.net/item/177585266-253033430-Inscribed%20Sylvan%20Guard's%20Bow/",
	"typedCount": 0,
	"visitCount": 1
},{
	"id": 59,
	"lastVisitTimeLocal": "07.04.2019, 13:21:13",
	"lastVisitTimeUTC": "2019-04-07T10:21:13.479Z",
	"title": "Bow of the Eldwurm's Touch | Магазин Dota 2",
	"url": "https://market.dota2.net/item/1198294385-3231973365-Bow%20of%20the%20Eldwurm's%20Touch/",
	"typedCount": 0,
	"visitCount": 1
},{
	"id": 58,
	"lastVisitTimeLocal": "07.04.2019, 13:21:10",
	"lastVisitTimeUTC": "2019-04-07T10:21:10.873Z",
	"title": "Longbow of the Boreal Watch | Магазин Dota 2",
	"url": "https://market.dota2.net/item/667401836-253033253-Longbow%20of%20the%20Boreal%20Watch/",
	"typedCount": 0,
	"visitCount": 1
},{
	"id": 57,
	"lastVisitTimeLocal": "07.04.2019, 13:21:04",
	"lastVisitTimeUTC": "2019-04-07T10:21:04.706Z",
	"title": "Купить предметы | Магазин Dota 2",
	"url": "https://market.dota2.net/?r=&q=&p=9",
	"typedCount": 0,
	"visitCount": 2
},{
	"id": 56,
	"lastVisitTimeLocal": "07.04.2019, 13:20:48",
	"lastVisitTimeUTC": "2019-04-07T10:20:48.868Z",
	"title": "Inscribed Pincher Bow | Магазин Dota 2",
	"url": "https://market.dota2.net/item/177585252-253032571-Inscribed%20Pincher%20Bow/",
	"typedCount": 0,
	"visitCount": 1
},{
	"id": 55,
	"lastVisitTimeLocal": "07.04.2019, 13:20:48",
	"lastVisitTimeUTC": "2019-04-07T10:20:48.528Z",
	"title": "Купить предметы | Магазин Dota 2",
	"url": "https://market.dota2.net/?r=&q=&p=8",
	"typedCount": 0,
	"visitCount": 2
},{
	"id": 54,
	"lastVisitTimeLocal": "07.04.2019, 13:20:43",
	"lastVisitTimeUTC": "2019-04-07T10:20:43.210Z",
	"title": "Complete Algid Legacy | Магазин Dota 2",
	"url": "https://market.dota2.net/item/3186760507-1625510296-Complete%20Algid%20Legacy/",
	"typedCount": 0,
	"visitCount": 1
},{
	"id": 53,
	"lastVisitTimeLocal": "07.04.2019, 13:20:35",
	"lastVisitTimeUTC": "2019-04-07T10:20:35.918Z",
	"title": "Купить предметы | Магазин Dota 2",
	"url": "https://market.dota2.net/?r=&q=&p=7",
	"typedCount": 0,
	"visitCount": 2
},{
	"id": 52,
	"lastVisitTimeLocal": "07.04.2019, 13:20:31",
	"lastVisitTimeUTC": "2019-04-07T10:20:31.591Z",
	"title": "Bow of the Eldwurm's Touch | Магазин Dota 2",
	"url": "https://market.dota2.net/item/630805298-3226783217-Bow%20of%20the%20Eldwurm's%20Touch/",
	"typedCount": 0,
	"visitCount": 1
},{
	"id": 51,
	"lastVisitTimeLocal": "07.04.2019, 13:20:27",
	"lastVisitTimeUTC": "2019-04-07T10:20:27.653Z",
	"title": "Купить предметы | Магазин Dota 2",
	"url": "https://market.dota2.net/?r=&q=&p=6",
	"typedCount": 0,
	"visitCount": 2
},{
	"id": 50,
	"lastVisitTimeLocal": "07.04.2019, 13:20:09",
	"lastVisitTimeUTC": "2019-04-07T10:20:09.008Z",
	"title": "Genuine Bow of the Howling Wind | Магазин Dota 2",
	"url": "https://market.dota2.net/item/116686109-57943528-Genuine%20Bow%20of%20the%20Howling%20Wind/",
	"typedCount": 0,
	"visitCount": 1
},{
	"id": 49,
	"lastVisitTimeLocal": "07.04.2019, 13:20:04",
	"lastVisitTimeUTC": "2019-04-07T10:20:04.601Z",
	"title": "Genuine Shade of the Ranger | Магазин Dota 2",
	"url": "https://market.dota2.net/item/582617362-3091988000-Genuine%20Shade%20of%20the%20Ranger/",
	"typedCount": 0,
	"visitCount": 1
},{
	"id": 48,
	"lastVisitTimeLocal": "07.04.2019, 13:20:00",
	"lastVisitTimeUTC": "2019-04-07T10:20:00.964Z",
	"title": "Купить предметы | Магазин Dota 2",
	"url": "https://market.dota2.net/?r=&q=&p=5",
	"typedCount": 0,
	"visitCount": 2
},{
	"id": 47,
	"lastVisitTimeLocal": "07.04.2019, 13:20:00",
	"lastVisitTimeUTC": "2019-04-07T10:20:00.774Z",
	"title": "Death Shadow Bow | Магазин Dota 2",
	"url": "https://market.dota2.net/item/698193677-1953824015-Death%20Shadow%20Bow/",
	"typedCount": 0,
	"visitCount": 1
},{
	"id": 46,
	"lastVisitTimeLocal": "07.04.2019, 13:19:44",
	"lastVisitTimeUTC": "2019-04-07T10:19:44.822Z",
	"title": "Купить предметы | Магазин Dota 2",
	"url": "https://market.dota2.net/?r=&q=&p=4",
	"typedCount": 0,
	"visitCount": 2
},{
	"id": 45,
	"lastVisitTimeLocal": "07.04.2019, 13:19:31",
	"lastVisitTimeUTC": "2019-04-07T10:19:31.903Z",
	"title": "Bow of the Frostborne Wayfarer | Магазин Dota 2",
	"url": "https://market.dota2.net/item/1506980620-1254693757-Bow%20of%20the%20Frostborne%20Wayfarer/",
	"typedCount": 0,
	"visitCount": 1
},{
	"id": 44,
	"lastVisitTimeLocal": "07.04.2019, 13:19:31",
	"lastVisitTimeUTC": "2019-04-07T10:19:31.001Z",
	"title": "Algid Legacy | Магазин Dota 2",
	"url": "https://market.dota2.net/item/1367163148-2659634030-Algid%20Legacy/",
	"typedCount": 0,
	"visitCount": 1
},{
	"id": 43,
	"lastVisitTimeLocal": "07.04.2019, 13:19:29",
	"lastVisitTimeUTC": "2019-04-07T10:19:29.582Z",
	"title": "Sylvan Guard's Bow | Магазин Dota 2",
	"url": "https://market.dota2.net/item/87638886-0-Sylvan%20Guard's%20Bow/",
	"typedCount": 0,
	"visitCount": 1
},{
	"id": 42,
	"lastVisitTimeLocal": "07.04.2019, 13:19:28",
	"lastVisitTimeUTC": "2019-04-07T10:19:28.401Z",
	"title": "Jeweled Longbow | Магазин Dota 2",
	"url": "https://market.dota2.net/item/87638801-0-Jeweled%20Longbow/",
	"typedCount": 0,
	"visitCount": 1
},{
	"id": 41,
	"lastVisitTimeLocal": "07.04.2019, 13:19:26",
	"lastVisitTimeUTC": "2019-04-07T10:19:26.514Z",
	"title": "Купить предметы | Магазин Dota 2",
	"url": "https://market.dota2.net/?r=&q=&p=3",
	"typedCount": 0,
	"visitCount": 2
},{
	"id": 36,
	"lastVisitTimeLocal": "07.04.2019, 13:18:51",
	"lastVisitTimeUTC": "2019-04-07T10:18:51.922Z",
	"title": "Genuine Bow of the Black Wind Raven | Магазин Dota 2",
	"url": "https://market.dota2.net/item/485599924-676100724-Genuine%20Bow%20of%20the%20Black%20Wind%20Raven/",
	"typedCount": 0,
	"visitCount": 2
},{
	"id": 40,
	"lastVisitTimeLocal": "07.04.2019, 13:18:51",
	"lastVisitTimeUTC": "2019-04-07T10:18:51.507Z",
	"title": "Death Shadow Bow | Магазин Dota 2",
	"url": "https://market.dota2.net/item/259977962-0-Death%20Shadow%20Bow/",
	"typedCount": 0,
	"visitCount": 1
},{
	"id": 39,
	"lastVisitTimeLocal": "07.04.2019, 13:18:51",
	"lastVisitTimeUTC": "2019-04-07T10:18:51.015Z",
	"title": "Genuine Bow of the Lone Traveler | Магазин Dota 2",
	"url": "https://market.dota2.net/item/533871083-0-Genuine%20Bow%20of%20the%20Lone%20Traveler/",
	"typedCount": 0,
	"visitCount": 1
},{
	"id": 38,
	"lastVisitTimeLocal": "07.04.2019, 13:18:43",
	"lastVisitTimeUTC": "2019-04-07T10:18:43.584Z",
	"title": "Ice Burst Bow | Магазин Dota 2",
	"url": "https://market.dota2.net/item/57939673-0-Ice%20Burst%20Bow/",
	"typedCount": 0,
	"visitCount": 1
},{
	"id": 33,
	"lastVisitTimeLocal": "07.04.2019, 13:18:41",
	"lastVisitTimeUTC": "2019-04-07T10:18:41.396Z",
	"title": "Ice Crystal Bow | Магазин Dota 2",
	"url": "https://market.dota2.net/item/66003896-0-Ice%20Crystal%20Bow/",
	"typedCount": 0,
	"visitCount": 2
},{
	"id": 37,
	"lastVisitTimeLocal": "07.04.2019, 13:18:40",
	"lastVisitTimeUTC": "2019-04-07T10:18:40.103Z",
	"title": "Auspicious Bow of the Howling Wind | Магазин Dota 2",
	"url": "https://market.dota2.net/item/340923200-704092699-Auspicious%20Bow%20of%20the%20Howling%20Wind/",
	"typedCount": 0,
	"visitCount": 1
},{
	"id": 35,
	"lastVisitTimeLocal": "07.04.2019, 13:18:39",
	"lastVisitTimeUTC": "2019-04-07T10:18:39.012Z",
	"title": "Bow of the Frostborne Wayfarer | Магазин Dota 2",
	"url": "https://market.dota2.net/item/1506980620-0-Bow%20of%20the%20Frostborne%20Wayfarer/",
	"typedCount": 0,
	"visitCount": 1
},{
	"id": 34,
	"lastVisitTimeLocal": "07.04.2019, 13:18:38",
	"lastVisitTimeUTC": "2019-04-07T10:18:38.954Z",
	"title": "Genuine Bow of the Black Wind Raven | Магазин Dota 2",
	"url": "https://market.dota2.net/item/485599924-0-Genuine%20Bow%20of%20the%20Black%20Wind%20Raven/",
	"typedCount": 0,
	"visitCount": 1
},{
	"id": 32,
	"lastVisitTimeLocal": "07.04.2019, 13:18:36",
	"lastVisitTimeUTC": "2019-04-07T10:18:36.599Z",
	"title": "Bow of the Shadowcat | Магазин Dota 2",
	"url": "https://market.dota2.net/item/241464411-627870542-Bow%20of%20the%20Shadowcat/",
	"typedCount": 0,
	"visitCount": 1
},{
	"id": 31,
	"lastVisitTimeLocal": "07.04.2019, 13:18:35",
	"lastVisitTimeUTC": "2019-04-07T10:18:35.774Z",
	"title": "Bow of the Wyvern Skin | Магазин Dota 2",
	"url": "https://market.dota2.net/item/985056661-0-Bow%20of%20the%20Wyvern%20Skin/",
	"typedCount": 0,
	"visitCount": 1
},{
	"id": 30,
	"lastVisitTimeLocal": "07.04.2019, 13:18:33",
	"lastVisitTimeUTC": "2019-04-07T10:18:33.717Z",
	"title": "Algid Legacy | Магазин Dota 2",
	"url": "https://market.dota2.net/item/1476404584-0-Algid%20Legacy/",
	"typedCount": 0,
	"visitCount": 1
},{
	"id": 29,
	"lastVisitTimeLocal": "07.04.2019, 13:18:31",
	"lastVisitTimeUTC": "2019-04-07T10:18:31.375Z",
	"title": "Longbow of the Boreal Watch | Магазин Dota 2",
	"url": "https://market.dota2.net/item/178701938-0-Longbow%20of%20the%20Boreal%20Watch/",
	"typedCount": 0,
	"visitCount": 1
},{
	"id": 28,
	"lastVisitTimeLocal": "07.04.2019, 13:18:31",
	"lastVisitTimeUTC": "2019-04-07T10:18:31.066Z",
	"title": "Купить предметы | Магазин Dota 2",
	"url": "https://market.dota2.net/?r=&q=&p=2",
	"typedCount": 0,
	"visitCount": 2
},{
	"id": 27,
	"lastVisitTimeLocal": "07.04.2019, 13:18:30",
	"lastVisitTimeUTC": "2019-04-07T10:18:30.263Z",
	"title": "Sentinel Bow | Магазин Dota 2",
	"url": "https://market.dota2.net/item/351745492-0-Sentinel%20Bow/",
	"typedCount": 0,
	"visitCount": 1
},{
	"id": 26,
	"lastVisitTimeLocal": "07.04.2019, 13:18:29",
	"lastVisitTimeUTC": "2019-04-07T10:18:29.754Z",
	"title": "Cold Case Bow | Магазин Dota 2",
	"url": "https://market.dota2.net/item/57939576-0-Cold%20Case%20Bow/",
	"typedCount": 0,
	"visitCount": 1
},{
	"id": 25,
	"lastVisitTimeLocal": "07.04.2019, 13:18:27",
	"lastVisitTimeUTC": "2019-04-07T10:18:27.421Z",
	"title": "Bow of the Shadowcat | Магазин Dota 2",
	"url": "https://market.dota2.net/item/241464411-0-Bow%20of%20the%20Shadowcat/",
	"typedCount": 0,
	"visitCount": 1
},{
	"id": 24,
	"lastVisitTimeLocal": "07.04.2019, 13:18:26",
	"lastVisitTimeUTC": "2019-04-07T10:18:26.289Z",
	"title": "Bow of the Howling Wind | Магазин Dota 2",
	"url": "https://market.dota2.net/item/340923200-340885147-%D0%A3%D0%B4%D0%B0%D1%87%D0%BB%D0%B8%D0%B2%D1%8B%D0%B9%20Bow%20of%20the%20Howling%20Wind/",
	"typedCount": 0,
	"visitCount": 1
},{
	"id": 23,
	"lastVisitTimeLocal": "07.04.2019, 13:18:19",
	"lastVisitTimeUTC": "2019-04-07T10:18:19.215Z",
	"title": "Bow of the Eldwurm's Touch | Магазин Dota 2",
	"url": "https://market.dota2.net/item/630805298-673362966-Bow%20of%20the%20Eldwurm's%20Touch/",
	"typedCount": 0,
	"visitCount": 1
},{
	"id": 22,
	"lastVisitTimeLocal": "07.04.2019, 13:18:18",
	"lastVisitTimeUTC": "2019-04-07T10:18:18.034Z",
	"title": "Genuine Bow of the Master Thief | Магазин Dota 2",
	"url": "https://market.dota2.net/item/360374097-0-Genuine%20Bow%20of%20the%20Master%20Thief/",
	"typedCount": 0,
	"visitCount": 1
},{
	"id": 21,
	"lastVisitTimeLocal": "07.04.2019, 13:18:14",
	"lastVisitTimeUTC": "2019-04-07T10:18:14.984Z",
	"title": "Bow of the Frostfangs | Магазин Dota 2",
	"url": "https://market.dota2.net/item/782548140-93973071-Bow%20of%20the%20Frostfangs/",
	"typedCount": 0,
	"visitCount": 1
},{
	"id": 20,
	"lastVisitTimeLocal": "07.04.2019, 13:18:13",
	"lastVisitTimeUTC": "2019-04-07T10:18:13.461Z",
	"title": "Bow of the Winged Bolt | Магазин Dota 2",
	"url": "https://market.dota2.net/item/673151364-0-Bow%20of%20the%20Winged%20Bolt/",
	"typedCount": 0,
	"visitCount": 1
},{
	"id": 19,
	"lastVisitTimeLocal": "07.04.2019, 13:18:12",
	"lastVisitTimeUTC": "2019-04-07T10:18:12.155Z",
	"title": "Bow of the Eldwurm's Touch | Магазин Dota 2",
	"url": "https://market.dota2.net/item/630805298-0-Bow%20of%20the%20Eldwurm's%20Touch/",
	"typedCount": 0,
	"visitCount": 1
}]
