[{
	"id": 59,
	"lastVisitTimeLocal": "08.04.2019, 21:04:19",
	"lastVisitTimeUTC": "2019-04-08T18:04:19.153Z",
	"title": "Inscribed Thud-Gun of the Keen Machine | Магазин Dota 2",
	"url": "https://market.dota2.net/item/681041142-3144154841-Inscribed%20Thud-Gun%20of%20the%20Keen%20Machine/",
	"typedCount": 0,
	"visitCount": 1
},{
	"id": 58,
	"lastVisitTimeLocal": "08.04.2019, 21:04:15",
	"lastVisitTimeUTC": "2019-04-08T18:04:15.048Z",
	"title": "Купить предметы | Магазин Dota 2",
	"url": "https://market.dota2.net/?r=&q=&p=8",
	"typedCount": 0,
	"visitCount": 2
},{
	"id": 57,
	"lastVisitTimeLocal": "08.04.2019, 21:04:12",
	"lastVisitTimeUTC": "2019-04-08T18:04:12.770Z",
	"title": "The Feeder-Eater | Магазин Dota 2",
	"url": "https://market.dota2.net/item/524843762-253033915-The%20Feeder-Eater/",
	"typedCount": 0,
	"visitCount": 1
},{
	"id": 56,
	"lastVisitTimeLocal": "08.04.2019, 21:04:10",
	"lastVisitTimeUTC": "2019-04-08T18:04:10.844Z",
	"title": "Inscribed Wolfhound Rifle | Магазин Dota 2",
	"url": "https://market.dota2.net/item/232488390-253045718-Inscribed%20Wolfhound%20Rifle/",
	"typedCount": 0,
	"visitCount": 1
},{
	"id": 55,
	"lastVisitTimeLocal": "08.04.2019, 21:04:08",
	"lastVisitTimeUTC": "2019-04-08T18:04:08.843Z",
	"title": "Dragon's Breath | Магазин Dota 2",
	"url": "https://market.dota2.net/item/442058204-57949762-Dragon's%20Breath/",
	"typedCount": 0,
	"visitCount": 1
},{
	"id": 54,
	"lastVisitTimeLocal": "08.04.2019, 21:04:06",
	"lastVisitTimeUTC": "2019-04-08T18:04:06.447Z",
	"title": "Купить предметы | Магазин Dota 2",
	"url": "https://market.dota2.net/?r=&q=&p=7",
	"typedCount": 0,
	"visitCount": 2
},{
	"id": 53,
	"lastVisitTimeLocal": "08.04.2019, 21:04:04",
	"lastVisitTimeUTC": "2019-04-08T18:04:04.871Z",
	"title": "Inscribed Cannon of the Occultist's Pursuit | Магазин Dota 2",
	"url": "https://market.dota2.net/item/2175810996-1636605108-Inscribed%20Cannon%20of%20the%20Occultist's%20Pursuit/",
	"typedCount": 0,
	"visitCount": 1
},{
	"id": 52,
	"lastVisitTimeLocal": "08.04.2019, 21:04:02",
	"lastVisitTimeUTC": "2019-04-08T18:04:02.312Z",
	"title": "Thud-Gun of the Keen Machine | Магазин Dota 2",
	"url": "https://market.dota2.net/item/1830314407-3097346303-Thud-Gun%20of%20the%20Keen%20Machine/",
	"typedCount": 0,
	"visitCount": 1
},{
	"id": 51,
	"lastVisitTimeLocal": "08.04.2019, 21:04:01",
	"lastVisitTimeUTC": "2019-04-08T18:04:01.187Z",
	"title": "Hare Hunt Rifle | Магазин Dota 2",
	"url": "https://market.dota2.net/item/1121817750-0-Hare%20Hunt%20Rifle/",
	"typedCount": 0,
	"visitCount": 1
},{
	"id": 50,
	"lastVisitTimeLocal": "08.04.2019, 21:03:58",
	"lastVisitTimeUTC": "2019-04-08T18:03:58.315Z",
	"title": "Купить предметы | Магазин Dota 2",
	"url": "https://market.dota2.net/?r=&q=&p=6",
	"typedCount": 0,
	"visitCount": 2
},{
	"id": 49,
	"lastVisitTimeLocal": "08.04.2019, 21:03:57",
	"lastVisitTimeUTC": "2019-04-08T18:03:57.365Z",
	"title": "Cursed Wolfhound Rifle | Магазин Dota 2",
	"url": "https://market.dota2.net/item/230298737-230139020-Cursed%20Wolfhound%20Rifle/",
	"typedCount": 0,
	"visitCount": 1
},{
	"id": 48,
	"lastVisitTimeLocal": "08.04.2019, 21:03:54",
	"lastVisitTimeUTC": "2019-04-08T18:03:54.976Z",
	"title": "Inscribed Karabin of the Wild West | Магазин Dota 2",
	"url": "https://market.dota2.net/item/408835425-414930508-Inscribed%20Karabin%20of%20the%20Wild%20West/",
	"typedCount": 0,
	"visitCount": 1
},{
	"id": 47,
	"lastVisitTimeLocal": "08.04.2019, 21:03:54",
	"lastVisitTimeUTC": "2019-04-08T18:03:54.410Z",
	"title": "Thud-Gun of the Keen Machine | Магазин Dota 2",
	"url": "https://market.dota2.net/item/962176595-3149773627-Thud-Gun%20of%20the%20Keen%20Machine/",
	"typedCount": 0,
	"visitCount": 1
},{
	"id": 46,
	"lastVisitTimeLocal": "08.04.2019, 21:03:52",
	"lastVisitTimeUTC": "2019-04-08T18:03:52.952Z",
	"title": "Rifle of the Great Safari | Магазин Dota 2",
	"url": "https://market.dota2.net/item/106611035-2920182650-Rifle%20of%20the%20Great%20Safari/",
	"typedCount": 0,
	"visitCount": 1
},{
	"id": 45,
	"lastVisitTimeLocal": "08.04.2019, 21:03:51",
	"lastVisitTimeUTC": "2019-04-08T18:03:51.228Z",
	"title": "Купить предметы | Магазин Dota 2",
	"url": "https://market.dota2.net/?r=&q=&p=5",
	"typedCount": 0,
	"visitCount": 2
},{
	"id": 44,
	"lastVisitTimeLocal": "08.04.2019, 21:03:50",
	"lastVisitTimeUTC": "2019-04-08T18:03:50.037Z",
	"title": "Inscribed Rifle of the Great Safari | Магазин Dota 2",
	"url": "https://market.dota2.net/item/231978304-253135211-Inscribed%20Rifle%20of%20the%20Great%20Safari/",
	"typedCount": 0,
	"visitCount": 1
},{
	"id": 43,
	"lastVisitTimeLocal": "08.04.2019, 21:03:47",
	"lastVisitTimeUTC": "2019-04-08T18:03:47.112Z",
	"title": "Inscribed Carbine of the Shooting Star | Магазин Dota 2",
	"url": "https://market.dota2.net/item/985849902-402506059-Inscribed%20Carbine%20of%20the%20Shooting%20Star/",
	"typedCount": 0,
	"visitCount": 1
},{
	"id": 42,
	"lastVisitTimeLocal": "08.04.2019, 21:03:45",
	"lastVisitTimeUTC": "2019-04-08T18:03:45.051Z",
	"title": "Купить предметы | Магазин Dota 2",
	"url": "https://market.dota2.net/?r=&q=&p=4",
	"typedCount": 0,
	"visitCount": 2
},{
	"id": 41,
	"lastVisitTimeLocal": "08.04.2019, 21:03:43",
	"lastVisitTimeUTC": "2019-04-08T18:03:43.867Z",
	"title": "Rifle of the Great Safari | Магазин Dota 2",
	"url": "https://market.dota2.net/item/106611035-57944754-Rifle%20of%20the%20Great%20Safari/",
	"typedCount": 0,
	"visitCount": 1
},{
	"id": 40,
	"lastVisitTimeLocal": "08.04.2019, 21:03:42",
	"lastVisitTimeUTC": "2019-04-08T18:03:42.351Z",
	"title": "Blunderbuss of the Longbeard Dwarf Engineer | Магазин Dota 2",
	"url": "https://market.dota2.net/item/1946983476-1625510296-Blunderbuss%20of%20the%20Longbeard%20Dwarf%20Engineer/",
	"typedCount": 0,
	"visitCount": 1
},{
	"id": 39,
	"lastVisitTimeLocal": "08.04.2019, 21:03:41",
	"lastVisitTimeUTC": "2019-04-08T18:03:41.329Z",
	"title": "Rifle of The Howling Wolf | Магазин Dota 2",
	"url": "https://market.dota2.net/item/340913385-340885147-%D0%A3%D0%B4%D0%B0%D1%87%D0%BB%D0%B8%D0%B2%D1%8B%D0%B9%20Rifle%20of%20The%20Howling%20Wolf/",
	"typedCount": 0,
	"visitCount": 1
},{
	"id": 38,
	"lastVisitTimeLocal": "08.04.2019, 21:03:39",
	"lastVisitTimeUTC": "2019-04-08T18:03:39.339Z",
	"title": "Купить предметы | Магазин Dota 2",
	"url": "https://market.dota2.net/?r=&q=&p=3",
	"typedCount": 0,
	"visitCount": 2
},{
	"id": 37,
	"lastVisitTimeLocal": "08.04.2019, 21:03:37",
	"lastVisitTimeUTC": "2019-04-08T18:03:37.989Z",
	"title": "Grampa Sharpie's Shin Shooter | Магазин Dota 2",
	"url": "https://market.dota2.net/item/129964924-57949762-Grampa%20Sharpie's%20Shin%20Shooter/",
	"typedCount": 0,
	"visitCount": 1
},{
	"id": 36,
	"lastVisitTimeLocal": "08.04.2019, 21:03:36",
	"lastVisitTimeUTC": "2019-04-08T18:03:36.410Z",
	"title": "Rifle of The Howling Wolf | Магазин Dota 2",
	"url": "https://market.dota2.net/item/253037292-626080326-Rifle%20of%20The%20Howling%20Wolf/",
	"typedCount": 0,
	"visitCount": 1
},{
	"id": 35,
	"lastVisitTimeLocal": "08.04.2019, 21:03:35",
	"lastVisitTimeUTC": "2019-04-08T18:03:35.675Z",
	"title": "Hare Hunt Rifle | Магазин Dota 2",
	"url": "https://market.dota2.net/item/210185748-0-Hare%20Hunt%20Rifle/",
	"typedCount": 0,
	"visitCount": 1
},{
	"id": 34,
	"lastVisitTimeLocal": "08.04.2019, 21:03:33",
	"lastVisitTimeUTC": "2019-04-08T18:03:33.932Z",
	"title": "The Instagib OSP | Магазин Dota 2",
	"url": "https://market.dota2.net/item/138049589-57949762-The%20Instagib%20OSP/",
	"typedCount": 0,
	"visitCount": 1
},{
	"id": 33,
	"lastVisitTimeLocal": "08.04.2019, 21:03:30",
	"lastVisitTimeUTC": "2019-04-08T18:03:30.860Z",
	"title": "Купить предметы | Магазин Dota 2",
	"url": "https://market.dota2.net/?r=&q=&p=2",
	"typedCount": 0,
	"visitCount": 2
},{
	"id": 32,
	"lastVisitTimeLocal": "08.04.2019, 21:03:29",
	"lastVisitTimeUTC": "2019-04-08T18:03:29.572Z",
	"title": "Carbine of the Shooting Star | Магазин Dota 2",
	"url": "https://market.dota2.net/item/985066933-0-Carbine%20of%20the%20Shooting%20Star/",
	"typedCount": 0,
	"visitCount": 1
},{
	"id": 31,
	"lastVisitTimeLocal": "08.04.2019, 21:03:28",
	"lastVisitTimeUTC": "2019-04-08T18:03:28.284Z",
	"title": "The Killstealer | Магазин Dota 2",
	"url": "https://market.dota2.net/item/128237747-0-The%20Killstealer/",
	"typedCount": 0,
	"visitCount": 1
},{
	"id": 30,
	"lastVisitTimeLocal": "08.04.2019, 21:03:27",
	"lastVisitTimeUTC": "2019-04-08T18:03:27.855Z",
	"title": "Hare Hunt Rifle | Магазин Dota 2",
	"url": "https://market.dota2.net/item/210185748-630781929-Hare%20Hunt%20Rifle/",
	"typedCount": 0,
	"visitCount": 1
},{
	"id": 29,
	"lastVisitTimeLocal": "08.04.2019, 21:03:27",
	"lastVisitTimeUTC": "2019-04-08T18:03:27.090Z",
	"title": "Wolfhound Rifle | Магазин Dota 2",
	"url": "https://market.dota2.net/item/190098330-0-Wolfhound%20Rifle/",
	"typedCount": 0,
	"visitCount": 1
},{
	"id": 28,
	"lastVisitTimeLocal": "08.04.2019, 21:03:25",
	"lastVisitTimeUTC": "2019-04-08T18:03:25.689Z",
	"title": "Muh Keen Gun | Магазин Dota 2",
	"url": "https://market.dota2.net/item/497885051-560542272-Muh%20Keen%20Gun/",
	"typedCount": 0,
	"visitCount": 1
},{
	"id": 27,
	"lastVisitTimeLocal": "08.04.2019, 21:03:25",
	"lastVisitTimeUTC": "2019-04-08T18:03:25.129Z",
	"title": "Blunderbuss of the Dwarf Engineer | Магазин Dota 2",
	"url": "https://market.dota2.net/item/1946934414-1625510296-Blunderbuss%20of%20the%20Dwarf%20Engineer/",
	"typedCount": 0,
	"visitCount": 1
},{
	"id": 26,
	"lastVisitTimeLocal": "08.04.2019, 21:03:24",
	"lastVisitTimeUTC": "2019-04-08T18:03:24.294Z",
	"title": "Stonefire | Магазин Dota 2",
	"url": "https://market.dota2.net/item/1479327217-0-Stonefire/",
	"typedCount": 0,
	"visitCount": 1
},{
	"id": 25,
	"lastVisitTimeLocal": "08.04.2019, 21:03:22",
	"lastVisitTimeUTC": "2019-04-08T18:03:22.488Z",
	"title": "Weapon of the Seasoned Expeditionary | Магазин Dota 2",
	"url": "https://market.dota2.net/item/2642246131-1625510296-Weapon%20of%20the%20Seasoned%20Expeditionary/",
	"typedCount": 0,
	"visitCount": 1
},{
	"id": 24,
	"lastVisitTimeLocal": "08.04.2019, 21:03:21",
	"lastVisitTimeUTC": "2019-04-08T18:03:21.779Z",
	"title": "Muh Keen Gun | Магазин Dota 2",
	"url": "https://market.dota2.net/item/497885051-497931736-Muh%20Keen%20Gun/",
	"typedCount": 0,
	"visitCount": 1
},{
	"id": 23,
	"lastVisitTimeLocal": "08.04.2019, 21:03:21",
	"lastVisitTimeUTC": "2019-04-08T18:03:21.123Z",
	"title": "Dragon's Breath | Магазин Dota 2",
	"url": "https://market.dota2.net/item/329949183-0-Dragon's%20Breath/",
	"typedCount": 0,
	"visitCount": 1
},{
	"id": 22,
	"lastVisitTimeLocal": "08.04.2019, 21:03:19",
	"lastVisitTimeUTC": "2019-04-08T18:03:19.261Z",
	"title": "Thud-Gun of the Keen Machine | Магазин Dota 2",
	"url": "https://market.dota2.net/item/673151348-0-Thud-Gun%20of%20the%20Keen%20Machine/",
	"typedCount": 0,
	"visitCount": 1
}]
